encipherpy/__init__.py
encipherpy/_punctuation.py
encipherpy/_rebuild_key.py
encipherpy/_string_number_convert.py
encipherpy/atbash_cipher.py
encipherpy/caesar_cipher.py
encipherpy/polybus_square_cipher.py
encipherpy/rot47_cipher.py
encipherpy/substitution_cipher.py
encipherpy/vigenere_cipher.py
encipherpy-2.2.0.dist-info/METADATA
encipherpy-2.2.0.dist-info/WHEEL
encipherpy-2.2.0.dist-info/licenses/LICENSE
encipherpy-2.2.0.dist-info/RECORD
